rdpower/__init__.py
rdpower/rdmde.py
rdpower/rdpower.py
rdpower/rdpower_fun.py
rdpower/rdsampsi.py
rdpower-1.0.0.dist-info/METADATA
rdpower-1.0.0.dist-info/WHEEL
rdpower-1.0.0.dist-info/top_level.txt
rdpower-1.0.0.dist-info/RECORD
