Metadata-Version: 2.1
Name: rdpower
Version: 1.0.0
Summary: Power Calculations for RD Designs
Home-page: https://github.com/rdpackages/rdpower
Author: Ricardo Masini
Author-email: rmasini@ucdavis.edu
Project-URL: Bug Tracker, https://github.com/rdpackages/rdpower/issues
Classifier: Programming Language :: Python :: 3
Classifier: License :: OSI Approved :: MIT License
Classifier: Operating System :: OS Independent
Requires-Python: >=3.6
Requires-Dist: numpy
Requires-Dist: scipy
Requires-Dist: rdrobust (>=1.1.0)
